{
    "recall": {
        "CMS": [
            [
                1.0
            ],
            [
                1.0
            ],
            [
                1.0
            ],
            [
                1.0
            ],
            [
                1.0
            ],
            [
                1.0
            ],
            [
                1.0
            ]
        ],
        "CMSIS-M1": [
            [
                0.9663416523672078
            ],
            [
                0.9960122843822347
            ],
            [
                0.9961435347934176
            ],
            [
                0.9986200659894254
            ],
            [
                0.9976140315877083
            ],
            [
                0.9984996437371652
            ],
            [
                0.9977833446181343
            ]
        ],
        "CMSIS-M2": [
            [
                0.7938060962206608
            ],
            [
                0.9724050932378312
            ],
            [
                0.9815501297000156
            ],
            [
                0.9852466334679689
            ],
            [
                0.9889439575509921
            ],
            [
                0.9768549743659743
            ],
            [
                0.9512842770702743
            ]
        ],
        "PRECISION": [
            [
                0.9162489485611591
            ],
            [
                0.9588300272721948
            ],
            [
                0.9861345424996214
            ],
            [
                0.9955087749923341
            ],
            [
                0.9959263153629099
            ],
            [
                0.9978133681496925
            ],
            [
                0.99823140070931
            ]
        ],
        "HashPipe": [
            [
                0.5431712954038239
            ],
            [
                0.7010863760596625
            ],
            [
                0.7349978729230238
            ],
            [
                0.840380960880979
            ],
            [
                0.8359205797199412
            ],
            [
                0.9502416566164399
            ],
            [
                0.954669225174682
            ]
        ],
        "FCM-Sketch": [
            [
                1.0
            ],
            [
                1.0
            ],
            [
                1.0
            ],
            [
                1.0
            ],
            [
                1.0
            ],
            [
                1.0
            ],
            [
                1.0
            ]
        ]
    },
    "precision": {
        "CMS": [
            [
                0.6335322660577769
            ],
            [
                0.8482336916058358
            ],
            [
                0.9445153214405643
            ],
            [
                0.9775334165690371
            ],
            [
                0.9802656062487717
            ],
            [
                0.9943395644671861
            ],
            [
                0.9977867772710538
            ]
        ],
        "CMSIS-M1": [
            [
                0.41957862226694514
            ],
            [
                0.797098551205683
            ],
            [
                0.9350114749132663
            ],
            [
                0.9677566448518397
            ],
            [
                0.9901013894397886
            ],
            [
                0.9954420561140515
            ],
            [
                0.9975717262592119
            ]
        ],
        "CMSIS-M2": [
            [
                0.480621459475761
            ],
            [
                0.8227221494247768
            ],
            [
                0.9235941415598785
            ],
            [
                0.9732389410706336
            ],
            [
                0.9904078235880787
            ],
            [
                0.9962426804131647
            ],
            [
                0.9982374179739982
            ]
        ],
        "PRECISION": [
            [
                0.989937789639075
            ],
            [
                0.99548052296684
            ],
            [
                0.9975763898581799
            ],
            [
                0.9983697919888801
            ],
            [
                0.9996568119775914
            ],
            [
                0.9999006986442242
            ],
            [
                1.0
            ]
        ],
        "HashPipe": [
            [
                1.0
            ],
            [
                1.0
            ],
            [
                1.0
            ],
            [
                1.0
            ],
            [
                1.0
            ],
            [
                1.0
            ],
            [
                1.0
            ]
        ],
        "FCM-Sketch": [
            [
                0.09647717431279498
            ],
            [
                0.4486384808167385
            ],
            [
                0.8514998501721449
            ],
            [
                0.9567322966149688
            ],
            [
                0.9849980252266788
            ],
            [
                0.9980097829279818
            ],
            [
                0.9995983710493913
            ]
        ]
    },
    "mse": {
        "CMS": [
            [
                472351424.1341275
            ],
            [
                98875417.81159136
            ],
            [
                20806805.689499147
            ],
            [
                4304956.932921219
            ],
            [
                1068329.3742157381
            ],
            [
                191866.21069588498
            ],
            [
                40638.654343426526
            ]
        ],
        "CMSIS-M1": [
            [
                1319894542.2373672
            ],
            [
                162454042.4859825
            ],
            [
                26701169.76126784
            ],
            [
                5200904.752970643
            ],
            [
                1078623.4826603844
            ],
            [
                176396.58232411376
            ],
            [
                60795.16277694018
            ]
        ],
        "CMSIS-M2": [
            [
                1306355819.3301184
            ],
            [
                160185579.8523215
            ],
            [
                29231987.02949979
            ],
            [
                4769615.562575372
            ],
            [
                1024475.5091808289
            ],
            [
                218051.55750998255
            ],
            [
                41470.10146414512
            ]
        ],
        "PRECISION": [
            [
                53171631.05961439
            ],
            [
                26796768.659175072
            ],
            [
                9626958.72739254
            ],
            [
                3762903.8044896657
            ],
            [
                874434.8128581725
            ],
            [
                145297.81496842846
            ],
            [
                53554.90539862643
            ]
        ],
        "HashPipe": [
            [
                355518273.02154994
            ],
            [
                288372441.06832814
            ],
            [
                262927648.0609656
            ],
            [
                134618239.61929467
            ],
            [
                211376326.54445317
            ],
            [
                51909451.06003369
            ],
            [
                37527940.38132486
            ]
        ],
        "FCM-Sketch": [
            [
                42807432433.403435
            ],
            [
                997028430.4137745
            ],
            [
                139030975.69055897
            ],
            [
                23603174.733072367
            ],
            [
                3566668.9568905914
            ],
            [
                512204.06165143824
            ],
            [
                79524.15913182899
            ]
        ]
    },
    "fnr": {
        "CMS": [
            [
                0.0
            ],
            [
                0.0
            ],
            [
                0.0
            ],
            [
                0.0
            ],
            [
                0.0
            ],
            [
                0.0
            ],
            [
                0.0
            ]
        ],
        "CMSIS-M1": [
            [
                0.00239051746374644
            ],
            [
                0.0002635022031639713
            ],
            [
                0.0002517655344615134
            ],
            [
                8.989110266287456e-05
            ],
            [
                0.00015518010735928134
            ],
            [
                9.755245633991547e-05
            ],
            [
                0.00014409909615172438
            ]
        ],
        "CMSIS-M2": [
            [
                0.013996858161138324
            ],
            [
                0.0018153194257742203
            ],
            [
                0.001204274802882138
            ],
            [
                0.0009598352215091553
            ],
            [
                0.0007186460775722502
            ],
            [
                0.0015026771542966976
            ],
            [
                0.0031571872844926192
            ]
        ],
        "PRECISION": [
            [
                0.005418148403205867
            ],
            [
                0.00266992766543106
            ],
            [
                0.0009006739500407255
            ],
            [
                0.0002919046444828023
            ],
            [
                0.0002647519396944769
            ],
            [
                0.00014212609591877793
            ],
            [
                0.00011495731361948348
            ]
        ],
        "HashPipe": [
            [
                0.028840387162692518
            ],
            [
                0.01906096203150989
            ],
            [
                0.01693513345012567
            ],
            [
                0.010269720812044232
            ],
            [
                0.010553668384850171
            ],
            [
                0.0032241889950854526
            ],
            [
                0.0029381389784473347
            ]
        ],
        "FCM-Sketch": [
            [
                0.0
            ],
            [
                0.0
            ],
            [
                0.0
            ],
            [
                0.0
            ],
            [
                0.0
            ],
            [
                0.0
            ],
            [
                0.0
            ]
        ]
    },
    "fpr": {
        "CMS": [
            [
                0.3664677339422231
            ],
            [
                0.15176630839416413
            ],
            [
                0.05548467855943577
            ],
            [
                0.02246658343096288
            ],
            [
                0.019734393751228305
            ],
            [
                0.0056604355328139025
            ],
            [
                0.0022132227289461868
            ]
        ],
        "CMSIS-M1": [
            [
                0.5804213777330549
            ],
            [
                0.202901448794317
            ],
            [
                0.06498852508673365
            ],
            [
                0.03224335514816031
            ],
            [
                0.009898610560211338
            ],
            [
                0.004557943885948523
            ],
            [
                0.0024282737407881755
            ]
        ],
        "CMSIS-M2": [
            [
                0.5193785405242389
            ],
            [
                0.17727785057522322
            ],
            [
                0.07640585844012154
            ],
            [
                0.026761058929366408
            ],
            [
                0.009592176411921376
            ],
            [
                0.0037573195868353935
            ],
            [
                0.0017625820260017864
            ]
        ],
        "PRECISION": [
            [
                0.01006221036092503
            ],
            [
                0.004519477033159978
            ],
            [
                0.0024236101418201126
            ],
            [
                0.001630208011119901
            ],
            [
                0.00034318802240866284
            ],
            [
                9.930135577587815e-05
            ],
            [
                0.0
            ]
        ],
        "HashPipe": [
            [
                0.0
            ],
            [
                0.0
            ],
            [
                0.0
            ],
            [
                0.0
            ],
            [
                0.0
            ],
            [
                0.0
            ],
            [
                0.0
            ]
        ],
        "FCM-Sketch": [
            [
                0.903522825687205
            ],
            [
                0.5513615191832615
            ],
            [
                0.14850014982785512
            ],
            [
                0.04326770338503112
            ],
            [
                0.015001974773321233
            ],
            [
                0.0019902170720181864
            ],
            [
                0.0004016289506086589
            ]
        ]
    }
}